{"cameraMode":{"drawMode":0,"name":"Shaded","section":"Shading Mode"},"sceneLighting":true,"audioPlay":false,"sceneViewState":{"m_AlwaysRefresh":false,"showFog":true,"showSkybox":true,"showFlares":true,"showImageEffects":true,"showParticleSystems":true,"showVisualEffectGraphs":true,"m_FxEnabled":true},"in2DMode":false,"pivot":{"x":49.87908172607422,"y":1.1188414096832276,"z":11.491732597351075},"rotation":{"x":0.14143788814544679,"y":0.6681268215179443,"z":-0.13147702813148499,"w":0.7187044620513916},"size":6.11477518081665,"orthographic":false}